ym_py_tool/__init__.py
ym_py_tool/config/__init__.py
ym_py_tool/config/config_tool.py
ym_py_tool/db/__init__.py
ym_py_tool/db/pg_tool.py
ym_py_tool/dir_tree_print.py
ym_py_tool-0.1.4.dist-info/LICENSE.txt
ym_py_tool-0.1.4.dist-info/METADATA
ym_py_tool-0.1.4.dist-info/WHEEL
ym_py_tool-0.1.4.dist-info/RECORD
