Metadata-Version: 2.3
Name: ym_py_tool
Version: 0.1.4
Summary: 
License: Apache License
Author: Yuanrenmao
Author-email: test@test.com
Requires-Python: >=3.10
Classifier: License :: Other/Proprietary License
Classifier: Programming Language :: Python :: 3
Classifier: Programming Language :: Python :: 3.10
Classifier: Programming Language :: Python :: 3.11
Classifier: Programming Language :: Python :: 3.12
Classifier: Programming Language :: Python :: 3.13
Requires-Dist: psycopg2-binary (>=2.9.10,<3.0.0)
